asmclient/__init__.py
asmclient/util/__init__.py
asmclient/util/util.py
asmclient-0.2.2.dist-info/LICENSE
asmclient-0.2.2.dist-info/METADATA
asmclient-0.2.2.dist-info/WHEEL
asmclient-0.2.2.dist-info/top_level.txt
asmclient-0.2.2.dist-info/RECORD
