Metadata-Version: 2.1
Name: asmclient
Version: 0.2.2
Summary: asmclient utility package
Home-page: UNKNOWN
Author: luoyw
License: Copyright (c) 2019 All yxt staff
Platform: UNKNOWN
Classifier: Programming Language :: Python :: 3
Classifier: Operating System :: OS Independent
License-File: LICENSE
